django_db_geventpool/__init__.py
django_db_geventpool/utils.py
django_db_geventpool/backends/__init__.py
django_db_geventpool/backends/base.py
django_db_geventpool/backends/creation.py
django_db_geventpool/backends/pool.py
django_db_geventpool/backends/postgis/__init__.py
django_db_geventpool/backends/postgis/base.py
django_db_geventpool/backends/postgresql_psycopg2/__init__.py
django_db_geventpool/backends/postgresql_psycopg2/base.py
django_db_geventpool/backends/postgresql_psycopg3/__init__.py
django_db_geventpool/backends/postgresql_psycopg3/base.py
django_db_geventpool-4.0.8.dist-info/METADATA
django_db_geventpool-4.0.8.dist-info/WHEEL
django_db_geventpool-4.0.8.dist-info/licenses/AUTHORS.rst
django_db_geventpool-4.0.8.dist-info/licenses/LICENSE
django_db_geventpool-4.0.8.dist-info/RECORD
