Metadata-Version: 2.4
Name: django-db-geventpool
Version: 4.0.8
Summary: Add a DB connection pool using gevent to django
Project-URL: Homepage, https://github.com/jneight/django-db-geventpool
Author-email: Javier Cordero Martinez <j@jcmz.me>
License-Expression: Apache-2.0
License-File: AUTHORS.rst
License-File: LICENSE
Classifier: Environment :: Web Environment
Classifier: Framework :: Django
Classifier: Framework :: Django :: 3.2
Classifier: Framework :: Django :: 4.2
Classifier: Framework :: Django :: 5.0
Classifier: Intended Audience :: Developers
Classifier: License :: OSI Approved :: Apache Software License
Classifier: Operating System :: OS Independent
Classifier: Programming Language :: Python
Classifier: Programming Language :: Python :: 3
Classifier: Topic :: Software Development :: Libraries :: Application Frameworks
Requires-Dist: django>=4.2
